./.gitignore
./.python-version
./1200_process.log
./PKG-INFO
./README.md
./binref_mcp.py
./language.json
./package_name
./push_info.json
./pyproject.toml
./server_config.json
./uv.lock
iflow_mcp_mrexodia_binref_mcp-0.1.1.dist-info/METADATA
iflow_mcp_mrexodia_binref_mcp-0.1.1.dist-info/WHEEL
iflow_mcp_mrexodia_binref_mcp-0.1.1.dist-info/entry_points.txt
iflow_mcp_mrexodia_binref_mcp-0.1.1.dist-info/RECORD
