Metadata-Version: 2.4
Name: iflow-mcp_mrexodia_binref-mcp
Version: 0.1.1
Summary: Add your description here
Requires-Python: >=3.11
Requires-Dist: binary-refinery[extended]>=0.9.12
Requires-Dist: zeromcp>=1.3.0
